arcade_github_api/__init__.py
arcade_github_api/moar/github.json
arcade_github_api/moar/openapi.json
arcade_github_api/tools/__init__.py
arcade_github_api/tools/request_body_schemas.py
arcade_github_api/wrapper_tools/AcceptGithubRepoInvitation.json
arcade_github_api/wrapper_tools/AddAppAccessRestrictions.json
arcade_github_api/wrapper_tools/AddCustomLabelsToRunner.json
arcade_github_api/wrapper_tools/AddEmailToGithubAccount.json
arcade_github_api/wrapper_tools/AddGithubAuthorizedSshKey.json
arcade_github_api/wrapper_tools/AddGithubReleaseReaction.json
arcade_github_api/wrapper_tools/AddGpgKeyToGithub.json
arcade_github_api/wrapper_tools/AddLabelsToGithubIssue.json
arcade_github_api/wrapper_tools/AddLabelsToRunner.json
arcade_github_api/wrapper_tools/AddOrUpdateGithubCollaborator.json
arcade_github_api/wrapper_tools/AddOrUpdateGithubTeamProjectPermissions.json
arcade_github_api/wrapper_tools/AddOrgAccessToRunnerGroup.json
arcade_github_api/wrapper_tools/AddProjectCollaborator.json
arcade_github_api/wrapper_tools/AddReactionToCommitComment.json
arcade_github_api/wrapper_tools/AddReactionToGithubComment.json
arcade_github_api/wrapper_tools/AddReactionToGithubIssue.json
arcade_github_api/wrapper_tools/AddReactionToGithubTeamDiscussion.json
arcade_github_api/wrapper_tools/AddReactionToPrComment.json
arcade_github_api/wrapper_tools/AddReactionToTeamDiscussionComment.json
arcade_github_api/wrapper_tools/AddRepoAccessToRunnerGroup.json
arcade_github_api/wrapper_tools/AddRepoToOrgSecret.json
arcade_github_api/wrapper_tools/AddRepoToOrgVariable.json
arcade_github_api/wrapper_tools/AddRepoToRequiredWorkflow.json
arcade_github_api/wrapper_tools/AddRepositoryToGithubInstallation.json
arcade_github_api/wrapper_tools/AddRepositoryToSecret.json
arcade_github_api/wrapper_tools/AddRunnerToGroup.json
arcade_github_api/wrapper_tools/AddSecurityManagerTeam.json
arcade_github_api/wrapper_tools/AddSelfHostedRunnerToGroup.json
arcade_github_api/wrapper_tools/AddSshKeyToGithubAccount.json
arcade_github_api-1.0.0.dist-info/METADATA
arcade_github_api-1.0.0.dist-info/WHEEL
arcade_github_api-1.0.0.dist-info/entry_points.txt
arcade_github_api-1.0.0.dist-info/licenses/LICENSE
arcade_github_api-1.0.0.dist-info/RECORD
